subquadratic_ops_torch/__init__.py
subquadratic_ops_torch/b2b_causal_conv1d.py
subquadratic_ops_torch/causal_conv1d.py
subquadratic_ops_torch/fft_causal_conv1d.py
subquadratic_ops_torch/fft_conv2d.py
subquadratic_ops_torch/implicit_filter.py
subquadratic_ops_torch/rearrange.py
subquadratic_ops_torch/utils.py
subquadratic_ops_torch/_ext/__init__.py
subquadratic_ops_torch/_ext/subquadratic_ops_torch_ext.cpython-313-aarch64-linux-gnu.so
subquadratic_ops_torch/_ext/kernel/__init__.py
subquadratic_ops_torch/_ext/kernel/implicit_filter.py
subquadratic_ops_torch/_ext/utils/__init__.py
subquadratic_ops_torch/_ext/utils/utils.py
subquadratic_ops_torch/include/gmock/gmock-actions.h
subquadratic_ops_torch/include/gmock/gmock-cardinalities.h
subquadratic_ops_torch/include/gmock/gmock-function-mocker.h
subquadratic_ops_torch/include/gmock/gmock-matchers.h
subquadratic_ops_torch/include/gmock/gmock-more-actions.h
subquadratic_ops_torch/include/gmock/gmock-more-matchers.h
subquadratic_ops_torch/include/gmock/gmock-nice-strict.h
subquadratic_ops_torch/include/gmock/gmock-spec-builders.h
subquadratic_ops_torch/include/gmock/gmock.h
subquadratic_ops_torch/include/gmock/internal/gmock-internal-utils.h
subquadratic_ops_torch/include/gmock/internal/gmock-port.h
subquadratic_ops_torch/include/gmock/internal/gmock-pp.h
subquadratic_ops_torch/include/gmock/internal/custom/README.md
subquadratic_ops_torch/include/gmock/internal/custom/gmock-generated-actions.h
subquadratic_ops_torch/include/gmock/internal/custom/gmock-matchers.h
subquadratic_ops_torch/include/gmock/internal/custom/gmock-port.h
subquadratic_ops_torch/include/gtest/gtest-assertion-result.h
subquadratic_ops_torch/include/gtest/gtest-death-test.h
subquadratic_ops_torch/include/gtest/gtest-matchers.h
subquadratic_ops_torch/include/gtest/gtest-message.h
subquadratic_ops_torch/include/gtest/gtest-param-test.h
subquadratic_ops_torch/include/gtest/gtest-printers.h
subquadratic_ops_torch_cu12-0.1.1.dist-info/METADATA
subquadratic_ops_torch_cu12-0.1.1.dist-info/WHEEL
subquadratic_ops_torch_cu12-0.1.1.dist-info/RECORD
subquadratic_ops_torch_cu12-0.1.1.dist-info/licenses/LICENSE
subquadratic_ops_torch_cu12-0.1.1.dist-info/licenses/Third_party_attr.txt
