Metadata-Version: 2.2
Name: subquadratic-ops-torch-cu12
Version: 0.1.1
Summary: subquadratic-ops-torch-cu12 - GPU Accelerated Torch Extensions for Subquadratic Operations
Author-Email: Alireza Moradzadeh <amoradzadeh@nvidia.com>
License: Other/Proprietary License (NVIDIA Proprietary Software)
Project-URL: Homepage, https://github.com/nvidia-digital-bio/subquadraticOps-docs
Project-URL: Documentation, https://nvidia-digital-bio.github.io/subquadraticOps-docs/index.html
Project-URL: Repository, https://github.com/nvidia-digital-bio/subquadraticOps-docs
Requires-Dist: scikit-build-core>=0.10
Requires-Dist: nanobind>=1.5.0
Requires-Dist: warp-lang>=1.8.0
Requires-Dist: nvidia-ml-py
